src/_internal/__init__.py
src/_internal/data_preprocessing.py
src/_internal/data_typing.py
src/_internal/exceptions.py
src/_internal/file_parser.py
src/_internal/info/ext.json
src/app/__init__.py
src/app/app.py
src/app/cli.py
src/app/helper.py
src/gui/__init__.py
src/gui/aio_components.py
src/gui/components.py
src/gui/filters.py
src/gui/assets/tooltip.js
src/gui/assets/css/style.css
src/gui/pages/dir_info.py
src/gui/pages/homepage.py
src/utility/__init__.py
src/utility/_version.py
src/utility/filters.py
src/utility/helper.py
src/utility/logs.py
src/utility/logging_configs/logs_config_file.json
src/utility/logging_configs/logs_config_file_old.json
src/utility/logging_configs/logs_config_file_old_prod.json
src/utility/logging_configs/logs_config_file_prod.json
project_visualization_tool_gdeluisi-1.0.2.dist-info/METADATA
project_visualization_tool_gdeluisi-1.0.2.dist-info/WHEEL
project_visualization_tool_gdeluisi-1.0.2.dist-info/entry_points.txt
project_visualization_tool_gdeluisi-1.0.2.dist-info/licenses/LICENSE
project_visualization_tool_gdeluisi-1.0.2.dist-info/RECORD
