Metadata-Version: 2.4
Name: project_visualization_tool_GDeLuisi
Version: 1.0.2
Summary: Visualization tool for git-managed projects
Project-URL: Homepage, https://github.com/GDeLuisi/project_visualization_tool
Project-URL: Issues, https://github.com/GDeLuisi/project_visualization_tool/issues
Project-URL: Repository, https://github.com/GDeLuisi/project_visualization_tool
Author-email: De Luisi Gerardo <deluisigerardo@gmail.com>
License-File: LICENSE
Keywords: git,projects,visualization-tool
Classifier: License :: OSI Approved :: GNU Affero General Public License v3 or later (AGPLv3+)
Classifier: Operating System :: OS Independent
Classifier: Programming Language :: Python :: 3.10
Classifier: Programming Language :: Python :: 3.11
Classifier: Programming Language :: Python :: 3.12
Classifier: Programming Language :: Python :: 3.13
Requires-Python: >=3.10
Requires-Dist: dash-ag-grid==31.3.1
Requires-Dist: dash-bootstrap-components==2.0.3
Requires-Dist: dash==3.1.0
Requires-Dist: pandas==2.3.0
Requires-Dist: repominer-gdeluisi>=1.5.0
Requires-Dist: truck-factor-gdeluisi>=1.2.1
Requires-Dist: waitress==3.0.2
Provides-Extra: test
Requires-Dist: pytest; extra == 'test'
Requires-Dist: pytest-cov; extra == 'test'
